{
  "color": {
    "orange": "#FF5A1F",
    "orangeDeep": "#E8430A",
    "cobalt": "#2E5BFF",
    "ink": "#0E1633",
    "haze": "#F5F6FA",
    "slate": "#5A6178",
    "line": "#E4E7F0",
    "cloud": "#FFFFFF"
  },
  "font": {
    "display": "Archivo, system-ui, sans-serif",
    "body": "Hanken Grotesk, system-ui, sans-serif",
    "mono": "Space Mono, ui-monospace, monospace"
  },
  "fontSize": {
    "h1": "60px", "h2": "40px", "h3": "26px",
    "lead": "20px", "body": "16px", "small": "14px", "caption": "12px", "stat": "24px"
  },
  "lineHeight": {
    "h1": 1.0, "h2": 1.05, "h3": 1.15, "lead": 1.5, "body": 1.6, "small": 1.5, "caption": 1.4
  },
  "spacing": { "1": "4px", "2": "8px", "3": "12px", "4": "16px", "5": "24px", "6": "32px", "7": "48px", "8": "64px" },
  "radius": { "sm": "8px", "md": "12px", "lg": "16px", "pill": "999px" },
  "shadow": {
    "card": "0 4px 16px rgba(14,22,51,0.08)",
    "pop": "0 12px 32px rgba(14,22,51,0.16)"
  }
}
